lcmap_tap/__init__.py
lcmap_tap/__main__.py
lcmap_tap/config-example.yaml
lcmap_tap/date_utils.py
lcmap_tap/logger.py
lcmap_tap/Analysis/__init__.py
lcmap_tap/Analysis/data_tools.py
lcmap_tap/Auxiliary/__init__.py
lcmap_tap/Auxiliary/caching.py
lcmap_tap/Auxiliary/projections.py
lcmap_tap/Auxiliary/tiles_with_data.kml
lcmap_tap/Controls/__init__.py
lcmap_tap/Controls/controls.py
lcmap_tap/MapCanvas/__init__.py
lcmap_tap/MapCanvas/geojson.py
lcmap_tap/MapCanvas/hv-tiles-cu.js
lcmap_tap/MapCanvas/mapcanvas.py
lcmap_tap/MapCanvas/UseWebEngineView/index.html
lcmap_tap/MapCanvas/UseWebEngineView/utils.css
lcmap_tap/MapCanvas/UseWebEngineView/utils.js
lcmap_tap/MapCanvas/UseWebView/index.html
lcmap_tap/MapCanvas/UseWebView/utils.css
lcmap_tap/MapCanvas/UseWebView/utils.js
lcmap_tap/PlotFrame/__init__.py
lcmap_tap/PlotFrame/plotwindow.py
lcmap_tap/PlotFrame/symbology_window.py
lcmap_tap/Plotting/__init__.py
lcmap_tap/Plotting/make_plots.py
lcmap_tap/Plotting/plot_config.py
lcmap_tap/Plotting/plot_functions.py
lcmap_tap/Plotting/plot_specs.py
lcmap_tap/RetrieveData/__init__.py
lcmap_tap/RetrieveData/ard_info.py
lcmap_tap/RetrieveData/grids.py
lcmap_tap/RetrieveData/http_client.py
lcmap_tap/RetrieveData/lcmaphttp.py
lcmap_tap/RetrieveData/merlin_cfg.py
lcmap_tap/RetrieveData/retrieve_ard.py
lcmap_tap/RetrieveData/retrieve_ccd.py
lcmap_tap/RetrieveData/retrieve_chips.py
lcmap_tap/RetrieveData/retrieve_geo.py
lcmap_tap/RetrieveData/tile_list.py
lcmap_tap/RetrieveData/tiles.py
lcmap_tap/UserInterface/__init__.py
lcmap_tap/UserInterface/ui_main_workshop.py
lcmap_tap/UserInterface/ui_symbology.py
lcmap_tap/Visualization/__init__.py
lcmap_tap/Visualization/chip_viewer.py
lcmap_tap/Visualization/chipviewer_main.py
lcmap_tap/Visualization/maps_viewer.py
lcmap_tap/Visualization/rescale.py
lcmap_tap/Visualization/tc_bgw_coeffs.py
lcmap_tap/Visualization/tc_calculations.py
lcmap_tap/Visualization/ui_maps_viewer.py
lcmap_tap/mapify/__init__.py
lcmap_tap/mapify/app.py
lcmap_tap-2.0.1.dist-info/LICENSE
lcmap_tap-2.0.1.dist-info/METADATA
lcmap_tap-2.0.1.dist-info/WHEEL
lcmap_tap-2.0.1.dist-info/entry_points.txt
lcmap_tap-2.0.1.dist-info/top_level.txt
lcmap_tap-2.0.1.dist-info/RECORD
