Metadata-Version: 2.1
Name: lcmap-tap
Version: 2.0.1
Summary: A data visualization tool for PyCCD time-series model results and Landsat ARD
Home-page: https://eroslab.cr.usgs.gov/lcmap/tap
Author: USGS EROS LCMAP
Author-email: 
License: Unlicense
Keywords: usgs eros lcmap
Platform: UNKNOWN
Classifier: Development Status :: 5 - Production/Stable
Classifier: License :: Public Domain
Classifier: Programming Language :: Python :: 3.6
Requires-Python: >=3.6
Requires-Dist: arrow
Requires-Dist: cryptography (==2.9)
Requires-Dist: cython
Requires-Dist: cytoolz
Requires-Dist: jinja2
Requires-Dist: matplotlib
Requires-Dist: pandas
Requires-Dist: PyQt5 (==5.10.1)
Requires-Dist: PyYaml
Requires-Dist: requests
Requires-Dist: lcmap-merlin (==2.3.1)
Provides-Extra: deploy
Requires-Dist: twine ; extra == 'deploy'
Provides-Extra: docs
Requires-Dist: sphinx ; extra == 'docs'
Requires-Dist: sphinx-autobuild ; extra == 'docs'
Requires-Dist: sphinx-rtd-theme ; extra == 'docs'
Provides-Extra: tests
Requires-Dist: pytest ; extra == 'tests'
Requires-Dist: pytest-cov ; extra == 'tests'
